<?xml version="1.0" encoding="UTF-8"?>
<!DOCTYPE suite SYSTEM "https://testng.org/testng-1.0.dtd">
<suite name="AmazonSuite">
 <parameter name="browser" value="edge"></parameter>
  <test thread-count="5" name="AmazonTestedge">
    <classes>
      <class name="AmazonPractice.LaunchAmazon"/>
    </classes>
  </test> <!-- Test -->
  <parameter name="browser" value="chrome"></parameter>
  <test thread-count="5" name="AmazonTestchrome">
    <classes>
      <class name="AmazonPractice.LaunchAmazon"/>
    </classes>
  </test> <!-- Test -->
</suite> <!-- Suite -->
